openldap_opencensus_stats/__init__.py
openldap_opencensus_stats/configuration.py
openldap_opencensus_stats/ldap_metric_set.py
openldap_opencensus_stats/ldap_server.py
openldap_opencensus_stats/ldap_statistic.py
openldap_opencensus_stats/ldap_sync_statistic.py
openldap_opencensus_stats/main.py
openldap_opencensus_stats/sync_metric_set.py
openldap_opencensus_stats/config_transformers/__init__.py
openldap_opencensus_stats/config_transformers/base.py
openldap_opencensus_stats/config_transformers/child_object.py
openldap_opencensus_stats/config_transformers/copy_for_each_database.py
openldap_opencensus_stats/config_transformers/metric_dn.py
openldap_opencensus_stats/config_transformers/metric_name.py
openldap_opencensus_stats/config_transformers/metric_name_interpolation.py
openldap_opencensus_stats/config_transformers/metric_query_dn.py
openldap_opencensus_stats/config_transformers/snake_case.py
openldap_opencensus_stats-0.0.15.data/data/etc/openldap-opencensus-stats.template.yml
openldap_opencensus_stats-0.0.15.dist-info/LICENSE
openldap_opencensus_stats-0.0.15.dist-info/METADATA
openldap_opencensus_stats-0.0.15.dist-info/WHEEL
openldap_opencensus_stats-0.0.15.dist-info/entry_points.txt
openldap_opencensus_stats-0.0.15.dist-info/top_level.txt
openldap_opencensus_stats-0.0.15.dist-info/RECORD
